PySrDaliGateway/__init__.py
PySrDaliGateway/__version__.py
PySrDaliGateway/base.py
PySrDaliGateway/const.py
PySrDaliGateway/device.py
PySrDaliGateway/discovery.py
PySrDaliGateway/exceptions.py
PySrDaliGateway/gateway.py
PySrDaliGateway/group.py
PySrDaliGateway/helper.py
PySrDaliGateway/panel.py
PySrDaliGateway/py.typed
PySrDaliGateway/scene.py
PySrDaliGateway/types.py
PySrDaliGateway/udp_client.py
PySrDaliGateway/certs/ca.crt
pysrdaligateway-0.19.3.dist-info/LICENSE
pysrdaligateway-0.19.3.dist-info/METADATA
pysrdaligateway-0.19.3.dist-info/WHEEL
pysrdaligateway-0.19.3.dist-info/top_level.txt
pysrdaligateway-0.19.3.dist-info/RECORD
