Metadata-Version: 2.1
Name: PySrDaliGateway
Version: 0.19.3
Summary: Python library for Sunricher DALI Gateway (EDA)
Author: Sunricher
License: Apache-2.0
Project-URL: Homepage, https://github.com/maginawin/PySrDaliGateway
Requires-Python: >=3.8
License-File: LICENSE
Requires-Dist: paho-mqtt>=1.6.0
Requires-Dist: psutil>=6.0.0
Requires-Dist: cryptography>=40.0.0
Provides-Extra: dev
Requires-Dist: mypy>=1.0.0; extra == "dev"
Requires-Dist: ruff>=0.12.1; extra == "dev"
